MANIFEST.in
README.md
setup.cfg
setup.py
sbanken/__init__.py
sbanken/client.py
sbanken.egg-info/PKG-INFO
sbanken.egg-info/SOURCES.txt
sbanken.egg-info/dependency_links.txt
sbanken.egg-info/requires.txt
sbanken.egg-info/top_level.txt