Metadata-Version: 1.1
Name: sbanken
Version: 1
Summary: Get bank account information from Sbanken in python
Home-page: https://github.com/lilleengen/sbanken
Author: Henrik Lilleengen
Author-email: henrik@lilleengen.io
License: UNKNOWN
Download-URL: https://github.com/lilleengen/sbanken/archive/0.1.tar.gz
Platform: UNKNOWN
Classifier: Programming Language :: Python :: 3
Classifier: License :: OSI Approved :: MIT License
Classifier: Operating System :: OS Independent
Classifier: Development Status :: 5 - Production/Stable
Classifier: Intended Audience :: Developers
Classifier: Topic :: Office/Business :: Financial
